llamazure/tf/__init__.py
llamazure/tf/models.py
llamazure/tf/network.py
llamazure.tf-0.2.0.dist-info/METADATA
llamazure.tf-0.2.0.dist-info/WHEEL
llamazure.tf-0.2.0.dist-info/namespace_packages.txt
llamazure.tf-0.2.0.dist-info/top_level.txt
llamazure.tf-0.2.0.dist-info/RECORD
